feriados_municipais_br/__init__.py
feriados_municipais_br/feriados_br.py
feriados_municipais_br-0.0.2.dist-info/LICENSE
feriados_municipais_br-0.0.2.dist-info/METADATA
feriados_municipais_br-0.0.2.dist-info/WHEEL
feriados_municipais_br-0.0.2.dist-info/top_level.txt
feriados_municipais_br-0.0.2.dist-info/RECORD
