Metadata-Version: 2.1
Name: feriados-municipais-br
Version: 0.0.2
Summary: Versão beta da biblioteca de feriados municipais.
Author: Luiz Fernando Teles Rodrigues
Author-email: euluizfernando2001@gmail.com
License: MIT License
Keywords: feriados br municipais brasil
Classifier: Programming Language :: Python :: 3
Classifier: License :: OSI Approved :: MIT License
Classifier: Operating System :: OS Independent
Requires-Python: >=3.6
License-File: LICENSE
Requires-Dist: datetime
